pytest_memlog/__init__.py
pytest_memlog/formatting.py
pytest_memlog/memlog.py
pytest_memlog/plugin.py
pytest_memlog-0.1.0a1.dist-info/LICENSE
pytest_memlog-0.1.0a1.dist-info/METADATA
pytest_memlog-0.1.0a1.dist-info/WHEEL
pytest_memlog-0.1.0a1.dist-info/entry_points.txt
pytest_memlog-0.1.0a1.dist-info/RECORD
