Metadata-Version: 2.1
Name: pytest-memlog
Version: 0.1.0a1
Summary: Log memory usage during tests
License: MIT
Author: Tamir Bahar
Requires-Python: >=3.8,<4.0
Classifier: Framework :: Pytest
Classifier: License :: OSI Approved :: MIT License
Classifier: Programming Language :: Python :: 3
Classifier: Programming Language :: Python :: 3.8
Classifier: Programming Language :: Python :: 3.9
Classifier: Programming Language :: Python :: 3.10
Classifier: Programming Language :: Python :: 3.11
Requires-Dist: psutil (>=5.9.5,<6.0.0)
Requires-Dist: pytest (>=7.3.0,<8.0.0)
Project-URL: repository, https://github.com/tmr232/pytest-memlog/
